torch_ecg/__init__.py
torch_ecg/cfg.py
torch_ecg/version.py
torch_ecg/_preprocessors/README.md
torch_ecg/_preprocessors/__init__.py
torch_ecg/_preprocessors/bandpass.py
torch_ecg/_preprocessors/base.py
torch_ecg/_preprocessors/baseline_remove.py
torch_ecg/_preprocessors/normalize.py
torch_ecg/_preprocessors/preproc_manager.py
torch_ecg/_preprocessors/resample.py
torch_ecg/augmenters/README.md
torch_ecg/augmenters/__init__.py
torch_ecg/augmenters/augmenter_manager.py
torch_ecg/augmenters/base.py
torch_ecg/augmenters/baseline_wander.py
torch_ecg/augmenters/cutmix.py
torch_ecg/augmenters/label_smooth.py
torch_ecg/augmenters/mixup.py
torch_ecg/augmenters/random_flip.py
torch_ecg/augmenters/random_masking.py
torch_ecg/augmenters/random_renormalize.py
torch_ecg/augmenters/stretch_compress.py
torch_ecg/components/README.md
torch_ecg/components/__init__.py
torch_ecg/components/inputs.py
torch_ecg/components/loggers.py
torch_ecg/components/metrics.py
torch_ecg/components/nas.py
torch_ecg/components/outputs.py
torch_ecg/components/trainer.py
torch_ecg/databases/README.md
torch_ecg/databases/__init__.py
torch_ecg/databases/base.py
torch_ecg/databases/requirements.txt
torch_ecg/databases/aux_data/__init__.py
torch_ecg/databases/aux_data/aha.py
torch_ecg/databases/aux_data/cinc2020_aux_data.py
torch_ecg/databases/aux_data/cinc2021_aux_data.py
torch_ecg/databases/aux_data/physionet_dbs.csv.gz
torch_ecg/databases/cpsc_databases/__init__.py
torch_ecg/databases/cpsc_databases/cpsc2018.py
torch_ecg/databases/cpsc_databases/cpsc2019.py
torch_ecg/databases/cpsc_databases/cpsc2020.py
torch_ecg/databases/cpsc_databases/cpsc2021.py
torch_ecg/databases/datasets/README.md
torch_ecg/databases/datasets/__init__.py
torch_ecg/databases/datasets/cinc2020/__init__.py
torch_ecg/databases/datasets/cinc2020/cinc2020_cfg.py
torch_ecg/databases/datasets/cinc2020/cinc2020_dataset.py
torch_ecg/databases/datasets/cinc2021/__init__.py
torch_ecg/databases/datasets/cinc2021/cinc2021_cfg.py
torch_ecg-0.0.30.dist-info/METADATA
torch_ecg-0.0.30.dist-info/WHEEL
torch_ecg-0.0.30.dist-info/licenses/LICENSE
torch_ecg-0.0.30.dist-info/RECORD
