Metadata-Version: 2.3
Name: torch-ecg
Version: 0.0.30
Summary: A Deep Learning Framework for ECG Processing Tasks Based on PyTorch
Project-URL: Homepage, https://github.com/DeepPSP/torch_ecg
Author-email: DeepPSP <wenh06@gmail.com>
License: MIT License
License-File: LICENSE
Classifier: License :: OSI Approved :: MIT License
Classifier: Operating System :: OS Independent
Classifier: Programming Language :: Python
Classifier: Programming Language :: Python :: 3
Classifier: Programming Language :: Python :: 3.7
Classifier: Programming Language :: Python :: 3.8
Classifier: Programming Language :: Python :: 3.9
Classifier: Programming Language :: Python :: 3.10
Classifier: Programming Language :: Python :: 3.11
Requires-Python: >=3.7
Requires-Dist: bib-lookup>=0.0.19
Requires-Dist: biosppy
Requires-Dist: cython
Requires-Dist: deprecate-kwargs
Requires-Dist: deprecated
Requires-Dist: einops
Requires-Dist: matplotlib
Requires-Dist: numpy<2.0.0
Requires-Dist: pandas
Requires-Dist: pyarrow
Requires-Dist: pyedflib
Requires-Dist: pywavelets
Requires-Dist: requests
Requires-Dist: scikit-learn
Requires-Dist: scipy
Requires-Dist: tensorboardx
Requires-Dist: torch
Requires-Dist: torch-optimizer
Requires-Dist: torchsummary
Requires-Dist: tqdm
Requires-Dist: typing-extensions
Requires-Dist: wfdb==3.2.0
Requires-Dist: xmltodict
Provides-Extra: dev
Requires-Dist: black==24.3.0; extra == 'dev'
Requires-Dist: flake8; extra == 'dev'
Requires-Dist: gdown; extra == 'dev'
Requires-Dist: librosa; extra == 'dev'
Requires-Dist: nbsphinx; extra == 'dev'
Requires-Dist: numpydoc; extra == 'dev'
Requires-Dist: openpyxl; extra == 'dev'
Requires-Dist: packaging; extra == 'dev'
Requires-Dist: pcg-springer-features; extra == 'dev'
Requires-Dist: pre-commit; extra == 'dev'
Requires-Dist: pydata-sphinx-theme; extra == 'dev'
Requires-Dist: pytest; extra == 'dev'
Requires-Dist: pytest-cov; extra == 'dev'
Requires-Dist: pytest-xdist; extra == 'dev'
Requires-Dist: sphinx-autobuild; extra == 'dev'
Requires-Dist: sphinx-book-theme; extra == 'dev'
Requires-Dist: sphinx-copybutton; extra == 'dev'
Requires-Dist: sphinx-design; extra == 'dev'
Requires-Dist: sphinx-emoji-favicon; extra == 'dev'
Requires-Dist: sphinx-markdown-tables; extra == 'dev'
Requires-Dist: sphinx-multiversion; extra == 'dev'
Requires-Dist: sphinx-rtd-theme; extra == 'dev'
Requires-Dist: sphinx-theme; extra == 'dev'
Requires-Dist: sphinx<7.0; extra == 'dev'
Requires-Dist: sphinxcontrib-bibtex; extra == 'dev'
Requires-Dist: sphinxcontrib-napoleon; extra == 'dev'
Requires-Dist: sphinxcontrib-tikz; extra == 'dev'
Requires-Dist: tensorboard; extra == 'dev'
Requires-Dist: torch-audiomentations; extra == 'dev'
Requires-Dist: torchaudio; extra == 'dev'
Provides-Extra: docs
Requires-Dist: nbsphinx; extra == 'docs'
Requires-Dist: numpydoc; extra == 'docs'
Requires-Dist: pydata-sphinx-theme; extra == 'docs'
Requires-Dist: sphinx-autobuild; extra == 'docs'
Requires-Dist: sphinx-book-theme; extra == 'docs'
Requires-Dist: sphinx-copybutton; extra == 'docs'
Requires-Dist: sphinx-design; extra == 'docs'
Requires-Dist: sphinx-emoji-favicon; extra == 'docs'
Requires-Dist: sphinx-markdown-tables; extra == 'docs'
Requires-Dist: sphinx-multiversion; extra == 'docs'
Requires-Dist: sphinx-rtd-theme; extra == 'docs'
Requires-Dist: sphinx-theme; extra == 'docs'
Requires-Dist: sphinx<7.0; extra == 'docs'
Requires-Dist: sphinxcontrib-bibtex; extra == 'docs'
Requires-Dist: sphinxcontrib-napoleon; extra == 'docs'
Requires-Dist: sphinxcontrib-tikz; extra == 'docs'
Provides-Extra: test
Requires-Dist: black==24.3.0; extra == 'test'
Requires-Dist: flake8; extra == 'test'
Requires-Dist: gdown; extra == 'test'
Requires-Dist: librosa; extra == 'test'
Requires-Dist: openpyxl; extra == 'test'
Requires-Dist: packaging; extra == 'test'
Requires-Dist: pcg-springer-features; extra == 'test'
Requires-Dist: pre-commit; extra == 'test'
Requires-Dist: pytest; extra == 'test'
Requires-Dist: pytest-cov; extra == 'test'
Requires-Dist: pytest-xdist; extra == 'test'
Requires-Dist: tensorboard; extra == 'test'
Requires-Dist: torch-audiomentations; extra == 'test'
Requires-Dist: torchaudio; extra == 'test'
